channels_postgres/__init__.py
channels_postgres/apps.py
channels_postgres/core.py
channels_postgres/db.py
channels_postgres/models.py
channels_postgres/migrations/0001_initial.py
channels_postgres/migrations/0002_create_triggers_and_functions.py
channels_postgres/migrations/0003_notify_smaller_payload.py
channels_postgres/migrations/0004_notify_ensure_payload_not_too_big.py
channels_postgres/migrations/__init__.py
channels_postgres-1.1.4.dist-info/licenses/LICENSE
channels_postgres-1.1.4.dist-info/METADATA
channels_postgres-1.1.4.dist-info/WHEEL
channels_postgres-1.1.4.dist-info/top_level.txt
channels_postgres-1.1.4.dist-info/RECORD
