Metadata-Version: 2.4
Name: channels_postgres
Version: 1.1.4
Summary: PostgreSQL-backed ASGI channel layer implementation
Author-email: Daniel Osaetin <f805nqs6j@relay.firefox.com>
License-Expression: MIT
Project-URL: Homepage, http://github.com/danidee10/channels_postgres/
Requires-Python: >=3.9
License-File: LICENSE
Requires-Dist: msgpack<2,>=1.0.7
Requires-Dist: asgiref<4,>=3.7.2
Requires-Dist: channels<5,>=4.0.0
Requires-Dist: psycopg[pool]<4,>=3
Provides-Extra: cryptography
Requires-Dist: cryptography<47,>=44.0.2; extra == "cryptography"
Provides-Extra: tests
Requires-Dist: async-timeout; extra == "tests"
Requires-Dist: cryptography<47,>=44.0.2; extra == "tests"
Requires-Dist: django-stubs<6,>=5.1.3; extra == "tests"
Requires-Dist: mypy<2,>=1.15.0; extra == "tests"
Requires-Dist: pylint<4,>=3.3.6; extra == "tests"
Requires-Dist: pylint-django<3,>=2.6.1; extra == "tests"
Requires-Dist: pytest<9,>=8.3.5; extra == "tests"
Requires-Dist: pytest-asyncio<1,>=0.26.0; extra == "tests"
Requires-Dist: pytest-cov<7,>=6.1.1; extra == "tests"
Requires-Dist: ruff<1,>=0.11.4; extra == "tests"
Dynamic: license-file
